macrometa_source_mysql/__init__.py
macrometa_source_mysql/connection.py
macrometa_source_mysql/discover_utils.py
macrometa_source_mysql/sample_data.py
macrometa_source_mysql/stream_utils.py
macrometa_source_mysql/sync_strategies/__init__.py
macrometa_source_mysql/sync_strategies/common.py
macrometa_source_mysql/sync_strategies/full_table.py
macrometa_source_mysql/sync_strategies/incremental.py
macrometa_source_mysql/sync_strategies/log_based.py
macrometa_source_mysql-0.0.18.dist-info/entry_points.txt
macrometa_source_mysql-0.0.18.dist-info/LICENSE
macrometa_source_mysql-0.0.18.dist-info/WHEEL
macrometa_source_mysql-0.0.18.dist-info/METADATA
macrometa_source_mysql-0.0.18.dist-info/RECORD
