Metadata-Version: 2.1
Name: macrometa-source-mysql
Version: 0.0.18
Summary: Macrometa Source for extracting data from MySQL database.
License: Apache-2.0
Keywords: ELT,Connectors,Workflows,Macrometa,MySQL,MariaDB,Source
Author: Macrometa
Author-email: info@macrometa.com
Requires-Python: >=3.8.1,<3.11
Classifier: License :: OSI Approved :: Apache Software License
Classifier: Programming Language :: Python :: 3
Classifier: Programming Language :: Python :: 3.9
Classifier: Programming Language :: Python :: 3.10
Classifier: Programming Language :: Python :: 3 :: Only
Classifier: Programming Language :: Python :: 3.8
Requires-Dist: PyMySQL (>=1.1.0)
Requires-Dist: c8connector (>=0.0.32)
Requires-Dist: mysql-replication (==0.43)
Requires-Dist: pendulum (==2.1.2)
Requires-Dist: pipelinewise-singer-python (==1.2.0)
Requires-Dist: plpygis (==0.2.1)
Requires-Dist: prometheus-client (==0.16.0)
Requires-Dist: tzlocal (==2.1)
Project-URL: Bug Tracker, https://github.com/Macrometacorp/macrometa-source-mysql/issues
